LICENSE.txt
MANIFEST.in
README.rst
requirements-test.txt
setup.py
jsonrpc_websocket/__init__.py
jsonrpc_websocket/jsonrpc.py
jsonrpc_websocket.egg-info/PKG-INFO
jsonrpc_websocket.egg-info/SOURCES.txt
jsonrpc_websocket.egg-info/dependency_links.txt
jsonrpc_websocket.egg-info/requires.txt
jsonrpc_websocket.egg-info/top_level.txt