Metadata-Version: 2.4
Name: jsonrpc-websocket
Version: 3.2.0
Summary: A JSON-RPC websocket client library for asyncio
Home-page: http://github.com/emlove/jsonrpc-websocket
Author: Emily Love Watson
Author-email: emily@emlove.me
License: BSD
Keywords: json-rpc async asyncio websocket
Classifier: Development Status :: 5 - Production/Stable
Classifier: Intended Audience :: Developers
Classifier: Topic :: Software Development :: Libraries
Classifier: License :: OSI Approved :: BSD License
Classifier: Programming Language :: Python :: 3
Classifier: Programming Language :: Python :: 3.9
Classifier: Programming Language :: Python :: 3.10
Classifier: Programming Language :: Python :: 3.11
Classifier: Programming Language :: Python :: 3.12
Classifier: Programming Language :: Python :: 3.13
License-File: LICENSE.txt
Requires-Dist: jsonrpc-base>=2.1.0
Requires-Dist: aiohttp>=3.0.0
Requires-Dist: async-timeout>=4.0.0
Dynamic: author
Dynamic: author-email
Dynamic: classifier
Dynamic: description
Dynamic: description-content-type
Dynamic: home-page
Dynamic: keywords
Dynamic: license
Dynamic: license-file
Dynamic: requires-dist
Dynamic: summary
